tcai_sandesh/__init__.py
tcai_sandesh/app.py
tcai_sandesh/static/images/tcai_logo.webp
tcai_sandesh/templates/index.html
tcai_sandesh/utils/__init__.py
tcai_sandesh/utils/analyze_audio.py
tcai_sandesh-1.0.0.dist-info/METADATA
tcai_sandesh-1.0.0.dist-info/WHEEL
tcai_sandesh-1.0.0.dist-info/entry_points.txt
tcai_sandesh-1.0.0.dist-info/top_level.txt
tcai_sandesh-1.0.0.dist-info/RECORD
